<!DOCTYPE ui:UiBinder SYSTEM "http://dl.google.com/gwt/DTD/xhtml.ent">
<ui:UiBinder
        xmlns:ui='urn:ui:com.google.gwt.uibinder'
        xmlns:g='urn:import:com.google.gwt.user.client.ui'
        xmlns:zfin='urn:import:org.zfin.gwt.root.ui'
        xmlns:zfin-mod='urn:import:org.zfin.gwt.curation.ui'
        >

    <g:FlowPanel>
        <zfin-mod:AttributionModule ui:field="attributionModule"/>
        <g:HTML>
            <hr/>
        </g:HTML>
        <zfin-mod:ExpressionExperimentZoneView ui:field="expressionExperimentZone"/>
        <zfin-mod:ExpressionZoneView ui:field="expressionZone"/>
        <zfin-mod:StructurePileView ui:field="structurePile"/>
        <zfin-mod:ConstructionZoneModule ui:field="constructionZoneModule"/>
    </g:FlowPanel>
</ui:UiBinder>
